{
    "name": "詹姆·兰尼斯特",
    "ac1":"詹姆生得高大英挺，金发飘扬，有着“闪亮的碧眼和利如刀锋的笑容”。他被公认是一名相貌英俊的美男子，还同时拥有迷人机智和冷酷傲慢两种截然相反的评价。<br>詹姆和瑟曦的长相非常相似，“像一个模子刻出的雕塑”。小时候他们甚至互换衣服假扮对方，连父亲泰温都看不出来。布兰·史塔克认为詹姆看上去像是“传说中的骑士”。作为御林铁卫的一员，詹姆身着白色盔甲，身披白色斗篷，不过他以自己的金甲闻名于世。手持镀金长剑，偶尔戴着嵌有雄狮的头盔。被俘一年后，詹姆的外貌彻底改变了。因为不允许清理，他现在脸上都是浓密的胡须，头发因许久不洗而打结。这次俘虏让他看上去瞬间老了五岁，面孔苍白、脸颊消瘦、双眼神凹。尽管如此，外人依旧可以一眼就看出他的帅气和魅力。为了在旅途中隐藏身份，詹姆修剪了发型，只留下下巴的黄色胡须。当他到达君临时，胡须又长出了一些，变成粗糙的胡渣。他的面颊依旧消瘦，下凹，下垂的眼袋让他又老了几岁。詹姆开始让头发和胡须恣意生长，不过一些头发已经开始变得灰白。<br>詹姆天生就是名战士，对政治和谋略小有兴趣，他很少将事情认真对待。他本人承认，仅有当战斗和做爱时候才有真正活着的感觉。他给旁人留下傲慢无理、是非不分、毁誉的印象杀死疯王令他声名狼藉，他说的每一句话最终都成为丑化自己的证据。此外，詹姆还非常轻率、顽固、易怒。大家都知道他没有耐心，并担心他的行为会带来严重的后果。詹姆作为一个伟大的战士，他的手下对他十分忠诚他英勇无比，不惧死亡。",
    "ac2":"三叉戟河之战的爆发促使泰温采取行动，他率兵抵达君临城下，以援军的名义请求进入。尽管瓦里斯认为泰温是叛徒，伊里斯国王还是听从派席尔大学士的建议，为泰温打开大门。一旦进入城中，泰温立刻调转矛头指向伊里斯，拉开了君临沦陷的帷幕。伊里斯得知后大怒，命令詹姆将他父亲的首级献上。詹姆没有听从命令，而是前去将受命毁灭全城的火术士罗萨特杀死，随后在铁王座下一剑割断伊里斯的喉咙，以防他将焚城命令下达给另一名火术士。<br>詹姆坐上铁王座，泰温公爵麾下的伊利·维斯特林爵士、罗兰德·克雷赫伯爵率领众人随即到来，目睹了詹姆所做的一切。他们询问是否要拥立新王，詹姆不置可否，只是坐在铁王座上，将染血的宝剑横陈于膝，静静等待下一个来人。这时，艾德·史塔克骑着马带领手下闯入大殿，对他声称王座应当归劳勃·拜拉席恩所有。<br>接下来的日子，詹姆暗中搜寻到剩下两个参与了伊里斯焚城计划的火术士：贝里斯和高苟思，然后杀了他们。[3] 尽管艾德·史塔克竭力抗争，坚称詹姆应当披上黑衣加入守夜人军团，劳勃国王还是赦免了他，让他继续留任御林铁卫。与此同时，劳勃也四处宣扬，让他的新名号弑君者闻名于世。<br>尽管背叛疯王的行为令他受尽各种辱骂，詹姆仍然认为杀死伊里斯是令他自豪的杰作。而他杀死疯王的真正动机，也从未被世人所知晓。",
    "ac3":"那个少年，从小想当亚瑟·戴恩，但不知怎地，生命拐了个弯，最后成为了微笑骑士。詹姆想着过去的自己",
    "name3":"Jaime Lannister",
    "img1":"character_img/Jaime1.jpg",
    "img2":"character_img/Jaime2.jpg",
    "bieming":"弑君者<br>兰尼斯特雄狮<br>残废",
    "touxian":"爵士<br>御林铁卫的队长<br>东境守护（前）",
    "shili":"兰尼斯特家族<br>御林铁卫",
    "wenhua":"维斯特洛",
    "chusheng":"266AC,出生于凯岩城",
    "peiou":"",
    "lianqing":"瑟曦·兰尼斯特"
}